env/bin/rst2html.py
env/bin/rst2html4.py
env/bin/rst2html5.py
env/bin/rst2latex.py
env/bin/rst2man.py
env/bin/rst2odt.py
env/bin/rst2odt_prepstyles.py
env/bin/rst2pseudoxml.py
env/bin/rst2s5.py
env/bin/rst2xetex.py
env/bin/rst2xml.py
env/bin/rstpep2html.py
jinx/README.md
jinx/__init__.py
jinx/jinx.py
jinx/request.py
jinx/response.py
jinx/middleware/__init__.py
jinx/middleware/middleware.py
jinx_web-0.0.9.dist-info/METADATA
jinx_web-0.0.9.dist-info/WHEEL
jinx_web-0.0.9.dist-info/top_level.txt
jinx_web-0.0.9.dist-info/RECORD
